django_render_as-1.3.dist-info/METADATA
django_render_as-1.3.dist-info/RECORD
django_render_as-1.3.dist-info/WHEEL
django_render_as-1.3.dist-info/top_level.txt
render_as/__init__.py
render_as/models.py
render_as/tests.py
render_as/templatetags/__init__.py
render_as/templatetags/render_as.py
render_as/test_templates/render_as/default_simple.html
render_as/test_templates/render_as/default_simple2.html
