Metadata-Version: 2.1
Name: django-render-as
Version: 1.3
Summary: Template rendering indirector based on object class
Home-page: UNKNOWN
Author: James Aylett
Author-email: james@tartarus.org
License: MIT
Platform: UNKNOWN
Classifier: Intended Audience :: Developers
Classifier: Framework :: Django
Classifier: License :: OSI Approved :: MIT License
Classifier: Programming Language :: Python :: 2
Classifier: Programming Language :: Python :: 3
Requires-Dist: Django (~=1.11)
